{
  "schema": "Core",
  "name": "_PackagingType",
  "description": "Packaging details ",
  "columns": [
    {
      "name": "_checks",
      "description": "References to the CheckActions performed on the object",
      "type": "_Check",
      "array": true,
      "codelist": true
    },
    {
      "name": "_externalReferences",
      "description": "References to all associated ExternalReferences",
      "type": "_ExternalReference",
      "array": true,
      "codelist": true
    },
    {
      "name": "_appliedOnPieces",
      "description": "Piece on which the Packaging type is applicable",
      "type": "_Piece",
      "array": true,
      "codelist": true
    },
    {
      "name": "_typeCode",
      "description": "Packaging type identifier as per UNECE Rec 21 Annex V and VI e.g. 1A - Drum; steel - Packaging material code. Identifies the Logistic Unit package type. UN Recommendation on Transport of Dangerous Goods; Model Regulations ",
      "type": "_CodeListElement",
      "array": false,
      "codelist": true
    },
    {
      "name": "_events",
      "description": "Events object",
      "type": "_LogisticsEvent",
      "array": true,
      "codelist": true
    },
    {
      "name": "_skeletonIndicator",
      "description": "Indicator whether a logistics object is a skeleton object",
      "type": "xsd_boolean",
      "array": false,
      "codelist": true
    },
    {
      "name": "_description",
      "description": "Natural language description if required",
      "type": "xsd_string",
      "array": false,
      "codelist": true
    }
  ]
}