{
  "schema": "Embedded",
  "name": "_LoosePiece",
  "description": "LoosePiece details",
  "columns": [
    {
      "name": "_pieceHeight",
      "description": "Height of a single piece",
      "type": "_Value",
      "array": false,
      "codelist": true
    },
    {
      "name": "_pieceLength",
      "description": "Length of a single piece",
      "type": "_Value",
      "array": false,
      "codelist": true
    },
    {
      "name": "_pieceWeight",
      "description": "Weight of a single piece",
      "type": "_Value",
      "array": false,
      "codelist": true
    },
    {
      "name": "_pieceWidth",
      "description": "Width of a single piece",
      "type": "_Value",
      "array": false,
      "codelist": true
    },
    {
      "name": "_dryIceWeight",
      "description": "Weight of dry ice",
      "type": "_Value",
      "array": false,
      "codelist": true
    },
    {
      "name": "_pieceGroupGrossWeight",
      "description": "Total gross weight of the piece group",
      "type": "_Value",
      "array": false,
      "codelist": true
    },
    {
      "name": "_stackable",
      "description": "Stackable indicator for the pieces (boolean)",
      "type": "xsd_boolean",
      "array": false,
      "codelist": true
    },
    {
      "name": "_turnable",
      "description": "Turnable indicator for the pieces (boolean)",
      "type": "xsd_boolean",
      "array": false,
      "codelist": true
    },
    {
      "name": "_pieceGroupCount",
      "description": "Number of pieces in the piece group",
      "type": "xsd_integer",
      "array": false,
      "codelist": true
    },
    {
      "name": "_pieceGroupId",
      "description": "Identifier of the piece group; increasing integers",
      "type": "xsd_integer",
      "array": false,
      "codelist": true
    }
  ]
}