{
  "name": "General.CustomsInformation",
  "description": "Customs information details",
  "schemaColor": "#91C4F2",
  "columns": [
    {
      "name": "contentCode",
      "description": "Customs; Security and Regulatory Control Information Identifier. Coded indicator qualifying Customs related information: Item Number 'I'; Exemption Legend 'L'; System Downtime Reference 'S'; Unique Consignment Reference Number 'U'; Movement Reference Number 'M' . Refers to Code List 1.1 Condition: At least one of the three elements (Country Code; Information Identifier or Customs; Security and Regulatory Control Information Identifier) must be completed",
      "type": "CodeListElement"
    },
    {
      "name": "country",
      "description": "Country details. Refer ISO 3166-2",
      "type": "CodeListElement"
    },
    {
      "name": "issuedForPiece",
      "description": "Reference to the Piece the document was issued for",
      "type": "Piece"
    },
    {
      "name": "issuedForShipment",
      "description": "Reference to the shipment the document was issued for",
      "type": "Shipment"
    },
    {
      "name": "subjectCode",
      "description": "Information Identifier. Code identifying a piece of information/entity e.g. 'IMP' for import; 'EXP' for export; 'AGT' for Agent; 'ISS' for The Regulated Agent Issuing the Security Status for a Consignment etc.  Condition: At least one of the three elements (Country Code; Information Identifier or Customs; Security and Regulatory Control Information Identifier) must be completed",
      "type": "CodeListElement"
    },
    {
      "name": "note",
      "description": "Free text for customs remarks; not used in OCI Composition Rules Table",
      "type": "string"
    },
    {
      "name": "otherCustomsInformation",
      "description": "Supplementary Customs; Security and Regulatory Control Information",
      "type": "string"
    },
    {
      "name": "checks",
      "description": "References to the CheckActions performed on the object",
      "type": "Check"
    },
    {
      "name": "events",
      "description": "Events object",
      "type": "LogisticsEvent"
    },
    {
      "name": "externalReferences",
      "description": "References to all associated ExternalReferences",
      "type": "ExternalReference"
    },
    {
      "name": "skeletonIndicator",
      "description": "Indicator whether a logistics object is a skeleton object",
      "type": "boolean"
    }
  ]
}